{
    "title": "Asking For Clear Skies",
    "description": "Authentic supplications for Asking For Clear Skies",
    "category": "asking-for-clear-skies",
    "seoContent": "Authentic invocations and supplications for Asking For Clear Skies. Derived from reliable sources including Hisnul Muslim.",
    "lastVerified": "2026-01-02",
    "items": [
        {
            "id": "asking-for-clear-skies-1",
            "slug": "asking-for-clear-skies-1",
            "title": "Dua 174",
            "arabic": "((اللَّهُمَّ حَوَالَيْنَا وَلاَ عَلَيْنَا، اللَّهُمَّ عَلَى الآكَامِ وَالظِّرَابِ، وَبُطُونِ الْأَوْدِيَةِ، وَمَنَابِتِ الشَّجَرِ)).",
            "transliteration": "Allahumma hawalayna wala AAalayna, allahumma AAalal-akami waththirab, wabutoonil-awdiyah, wamanabitish-shajar.",
            "translation": "O Allah, let the rain fall around us and not upon us, O Allah, (let it fall) on the pastures, hills, valleys and the roots of trees.",
            "count": 1,
            "source": {
                "collection": "Hisnul Muslim",
                "reference": ""
            },
            "virtue": "",
            "lastVerified": "2026-01-02",
            "authenticity": "Sahih",
            "audioFile": "174.mp3"
        }
    ]
}