{
    "title": "Breaking Fast At Someones House",
    "description": "Authentic supplications for Breaking Fast At Someones House",
    "category": "breaking-fast-at-someones-house",
    "seoContent": "Authentic invocations and supplications for Breaking Fast At Someones House. Derived from reliable sources including Hisnul Muslim.",
    "lastVerified": "2026-01-02",
    "items": [
        {
            "id": "breaking-fast-at-someones-house-1",
            "slug": "breaking-fast-at-someones-house-1",
            "title": "Dua 184",
            "arabic": " ((أَفْطَرَ عِنْدَكُمُ الصَّائِمُونَ، وَأَكَلَ طَعَامَكُمُ الْأَبْرَارُ، وَصَلَّتْ عَلَيْكُمُ الْمَلاَئِكَةُ)).",
            "transliteration": "Aftara AAindakumus-sa-imoon, wa-akala taAAamakumul-abrar, wasallat AAalaykumul-mala-ikah.",
            "translation": "May the fasting break their fast in your home, and may the dutiful and pious eat your food, and may the angles send prayers upon you.",
            "count": 1,
            "source": {
                "collection": "Hisnul Muslim",
                "reference": ""
            },
            "virtue": "",
            "lastVerified": "2026-01-02",
            "authenticity": "Sahih",
            "audioFile": "184.mp3",
            "title_ar": "دعاء 184"
        }
    ],
    "title_ar": "المنزل",
    "description_ar": "من الأذكار والأدعية الصحيحة: المنزل"
}