{
    "title": "Loving For Allah Dua",
    "description": "Authentic supplications for Loving For Allah Dua",
    "category": "loving-for-allah-dua",
    "seoContent": "Authentic invocations and supplications for Loving For Allah Dua. Derived from reliable sources including Hisnul Muslim.",
    "lastVerified": "2026-01-02",
    "items": [
        {
            "id": "loving-for-allah-dua-1",
            "slug": "loving-for-allah-dua-1",
            "title": "Dua 200",
            "arabic": "((أَحَبَّكَ الَّذِي أَحْبَبْتَنِي لَهُ)).",
            "transliteration": "Ahabbakal-lathee ahbabtanee lah.",
            "translation": "May He, for whom you have loved me, love you.",
            "count": 1,
            "source": {
                "collection": "Hisnul Muslim",
                "reference": ""
            },
            "virtue": "",
            "lastVerified": "2026-01-02",
            "authenticity": "Sahih",
            "audioFile": "200.mp3"
        }
    ]
}